{
  "input": [
    {
      "type": "text",
      "action": "add",
      "args": {
        "name": "direct",
        "uri": "./output/text/ru.txt"
      }
    },
    {
      "type": "text",
      "action": "add",
      "args": {
        "name": "direct",
        "uri": "./output/text/by.txt"
      }
    },
    {
      "type": "text",
      "action": "add",
      "args": {
        "name": "direct",
        "uri": "./output/text/kz.txt"
      }
    },
    {
      "type": "text",
      "action": "add",
      "args": {
        "name": "direct",
        "uri": "./CUSTOM-LIST-ADD.txt"
      }
    },
    {
      "type": "text",
      "action": "add",
      "args": {
        "name": "direct",
        "uri": "./output/text/private.txt"
      }
    },
    {
      "type": "text",
      "action": "add",
      "args": {
        "name": "proxy",
        "uri": "./antifilter.txt"
      }
    },
    {
      "type": "text",
      "action": "add",
      "args": {
        "name": "proxy",
        "uri": "./refilter.txt"
      }
    },
    {
      "type": "text",
      "action": "add",
      "args": {
        "name": "proxy",
        "uri": "./refiltercommunity.txt"
      }
    }
  ],
  "output": [
    {
      "type": "v2rayGeoIPDat",
      "action": "output",
      "args": {
        "outputName": "geoip.dat"
      }
    },
    {
      "type": "text",
      "action": "output"
    }
  ]
}
